geomapviz/__init__.py
geomapviz/aggregator.py
geomapviz/plot.py
geomapviz/shapefiles.py
geomapviz/utils.py
geomapviz/bckgd/belgium_hd.tif
geomapviz/bckgd/belgium_md.tif
geomapviz/bckgd/belgium_sd.tif
geomapviz/bckgd/nl_hd.tif
geomapviz/bckgd/nl_md.tif
geomapviz/bckgd/nl_sd.tif
geomapviz/data/app_data.txt.gz
geomapviz/shp/belgium.cpg
geomapviz/shp/belgium.dbf
geomapviz/shp/belgium.shp
geomapviz/shp/belgium.shx
geomapviz/shp/nl_pc4_2014.dbf
geomapviz/shp/nl_pc4_2014.prj
geomapviz/shp/nl_pc4_2014.shp
geomapviz/shp/nl_pc4_2014.shx
geomapviz-1.1.3.dist-info/LICENSE.md
geomapviz-1.1.3.dist-info/METADATA
geomapviz-1.1.3.dist-info/WHEEL
geomapviz-1.1.3.dist-info/top_level.txt
geomapviz-1.1.3.dist-info/RECORD
