Metadata-Version: 2.1
Name: geomapviz
Version: 1.1.3
Summary: data visualization on maps with varying levels of granularity
Author-email: Thomas Bury <bury.thomas@gmail.com>
License: MIT License
Project-URL: homepage, https://github.com/ThomasBury/geomapviz
Project-URL: documentation, https://github.com/ThomasBury/geomapviz
Project-URL: repository, https://github.com/ThomasBury/geomapviz.git
Project-URL: changelog, https://github.com/ThomasBury/geomapviz
Project-URL: Tracker, https://github.com/ThomasBury/geomapviz/issues
Keywords: geographical,visualization,map,interactive,choropleth
Classifier: Programming Language :: Python :: 3
Requires-Python: >=3.8
License-File: LICENSE.md
Requires-Dist: holoviews >=1.14.8
Requires-Dist: geoviews
Requires-Dist: matplotlib >=3.5
Requires-Dist: numpy >=1.21
Requires-Dist: pandas >=1.4
Requires-Dist: geopandas
Requires-Dist: mapclassify
Requires-Dist: contextily
Requires-Dist: panel >=0.13
Requires-Dist: scipy >=1.8.0
Requires-Dist: seaborn >=0.11.2
Requires-Dist: tqdm >=4.62.3
Requires-Dist: cartopy
Provides-Extra: doc
Requires-Dist: ipykernel ; extra == 'doc'
Requires-Dist: ipython-genutils ; extra == 'doc'
Requires-Dist: pandoc ; extra == 'doc'
Requires-Dist: sphinx ; extra == 'doc'
Requires-Dist: sphinxawesome-theme ==4.1.0 ; extra == 'doc'
Requires-Dist: nbsphinx ==0.9.2 ; extra == 'doc'
Requires-Dist: sphinx-autodoc-typehints <1.24.0 ; extra == 'doc'
Requires-Dist: sphinx-copybutton ==0.5.2 ; extra == 'doc'
Requires-Dist: sphinx-tabs ==3.4.1 ; extra == 'doc'
Provides-Extra: lint
Requires-Dist: black ; extra == 'lint'
Requires-Dist: flake8 ; extra == 'lint'
Provides-Extra: test
Requires-Dist: pytest ; extra == 'test'
Requires-Dist: pytest-cov ; extra == 'test'
